commit_memory/__init__.py
commit_memory/__main__.py
commit_memory/cli.py
commit_memory/git_service.py
commit_memory/json_compat.py
commit_memory/memoService.py
commit_memory/memo_formatter.py
commit_memory/memo_store.py
commit_memory/models.py
commit_memory/security.py
commit_memory/trust.py
commit_memory/validation.py
commit_memory-0.1.6.dist-info/licenses/LICENSE
commit_memory-0.1.6.dist-info/METADATA
commit_memory-0.1.6.dist-info/WHEEL
commit_memory-0.1.6.dist-info/entry_points.txt
commit_memory-0.1.6.dist-info/top_level.txt
commit_memory-0.1.6.dist-info/RECORD
