Metadata-Version: 2.4
Name: commit-memory
Version: 0.1.6
Summary: A Git companion tool that allows you to attach notes and memos to specific commits and file lines in your Git repository
Author: Ilia Lataria
License: MIT
Project-URL: Homepage, https://github.com/StarFleet1334/commit-memory
Project-URL: Bug Tracker, https://github.com/StarFleet1334/commit-memory/issues
Classifier: Programming Language :: Python :: 3
Classifier: Programming Language :: Python :: 3.9
Classifier: License :: OSI Approved :: MIT License
Classifier: Operating System :: OS Independent
Requires-Python: >=3.9
License-File: LICENSE
Requires-Dist: typer>=0.9
Requires-Dist: rich>=13
Requires-Dist: GitPython>=3.1
Requires-Dist: PyYAML>=6.0.1
Provides-Extra: test
Requires-Dist: pytest>=7.0.0; extra == "test"
Requires-Dist: pytest-mock>=3.10.0; extra == "test"
Requires-Dist: pytest-cov>=4.1.0; extra == "test"
Dynamic: license-file
